MANIFEST.in
README.md
setup.cfg
setup.py
dbex/__init__.py
dbex/decoder.py
dbex/encoder.py
dbex/encryption.py
dbex/globalv.py
dbex/sort_items.py
dbex.egg-info/PKG-INFO
dbex.egg-info/SOURCES.txt
dbex.egg-info/dependency_links.txt
dbex.egg-info/not-zip-safe
dbex.egg-info/top_level.txt
test/test_decoder.py
test/test_encoder.py
test/test_encryption.py
test/test_init_.py
test/test_sort_items.py